mocpy-0.19.1.dist-info/METADATA
mocpy-0.19.1.dist-info/WHEEL
mocpy-0.19.1.dist-info/licenses/LICENSE
mocpy.libs/libdl-360dee19.so.2
mocpy.libs/libgcc_s-0107df99.so.1
mocpy.libs/libm-f6cb68bf.so.6
mocpy.libs/libpthread-ab368e0d.so.0
mocpy/__init__.py
mocpy/abstract_moc.py
mocpy/fmoc/__init__.py
mocpy/fmoc/fmoc.py
mocpy/moc/__init__.py
mocpy/moc/boundaries.py
mocpy/moc/moc.py
mocpy/moc/plot/__init__.py
mocpy/moc/plot/border.py
mocpy/moc/plot/culling_backfacing_cells.py
mocpy/moc/plot/fill.py
mocpy/moc/plot/utils.py
mocpy/moc/plot/wcs.py
mocpy/mocpy.cpython-39-aarch64-linux-gnu.so
mocpy/serializer.py
mocpy/sfmoc/__init__.py
mocpy/sfmoc/sfmoc.py
mocpy/stmoc/__init__.py
mocpy/stmoc/stmoc.py
mocpy/tests/__init__.py
mocpy/tests/test_abstract_moc.py
mocpy/tests/test_fmoc.py
mocpy/tests/test_moc.py
mocpy/tests/test_polygon.py
mocpy/tests/test_sfmoc.py
mocpy/tests/test_stmoc.py
mocpy/tests/test_tmoc.py
mocpy/tmoc/__init__.py
mocpy/tmoc/tmoc.py
mocpy/version.py
mocpy-0.19.1.dist-info/RECORD
